watson/__init__.py
watson/db/__init__.py
watson/db/commands.py
watson/db/contextmanagers.py
watson/db/engine.py
watson/db/fixtures.py
watson/db/listeners.py
watson/db/meta.py
watson/db/models.py
watson/db/panels.py
watson/db/repositories.py
watson/db/services.py
watson/db/session.py
watson/db/utils.py
watson/db/alembic/templates/watson/README
watson/db/alembic/templates/watson/alembic.ini.mako
watson/db/alembic/templates/watson/env.py
watson/db/alembic/templates/watson/script.py.mako
watson/db/debug/__init__.py
watson/db/debug/panels.py
watson/db/debug/views/debug/panels/database.html
watson_db-2.7.1.dist-info/AUTHORS
watson_db-2.7.1.dist-info/LICENSE
watson_db-2.7.1.dist-info/METADATA
watson_db-2.7.1.dist-info/WHEEL
watson_db-2.7.1.dist-info/top_level.txt
watson_db-2.7.1.dist-info/RECORD
