Metadata-Version: 2.1
Name: watson-db
Version: 2.7.1
Summary: SqlAlchemy integration into Watson.
Home-page: http://github.com/watsonpy/watson-db
Author: Simon Coulton
Author-email: simon@bespohk.com
License: Copyright (c) Bespohk and individual contributors.
Requires-Dist: watson-framework (>=3.4.6)
Requires-Dist: sqlalchemy (>=1.0.14)
Requires-Dist: alembic (>=0.8.6)
Requires-Dist: sqlacodegen (>=1.1.6)
Provides-Extra: test
Requires-Dist: pytest ; extra == 'test'
Requires-Dist: pytest-cov ; extra == 'test'
Requires-Dist: coverage ; extra == 'test'
Requires-Dist: coveralls ; extra == 'test'
